L3rotect/AntiAnalysis.py
L3rotect/__init__.py
L3_rotect-0.2.dist-info/METADATA
L3_rotect-0.2.dist-info/WHEEL
L3_rotect-0.2.dist-info/top_level.txt
L3_rotect-0.2.dist-info/RECORD
